cipher_simon/__init__.py
cipher_simon/simon.py
simon_cipher-0.1.1.dist-info/METADATA
simon_cipher-0.1.1.dist-info/WHEEL
simon_cipher-0.1.1.dist-info/top_level.txt
simon_cipher-0.1.1.dist-info/RECORD
