Metadata-Version: 2.1
Name: simon-cipher
Version: 0.1.1
Summary: Python implementation of the Simon cipher
Author: Azaliya
Author-email: azakhabi19@gmail.com
Classifier: Programming Language :: Python :: 3
Classifier: License :: OSI Approved :: MIT License
Classifier: Operating System :: OS Independent
Requires-Python: >=3.6
